[{"State":"Ohio","Pop":11689442,"Year":"2018","per_US":3.5725678484,"quantile":"1st"},{"State":"Puerto Rico","Pop":3195153,"Year":"2018","per_US":0.9765137531,"quantile":"3rd"},{"State":"Alabama","Pop":4887871,"Year":"2018","per_US":1.4938481051,"quantile":"2nd"},{"State":"Wisconsin","Pop":5813568,"Year":"2018","per_US":1.7767628362,"quantile":"2nd"},{"State":"Alaska","Pop":737438,"Year":"2018","per_US":0.2253783619,"quantile":"4th"},{"State":"West Virginia","Pop":1805832,"Year":"2018","per_US":0.5519046455,"quantile":"3rd"},{"State":"Washington","Pop":7535591,"Year":"2018","per_US":2.3030534841,"quantile":"1st"},{"State":"Arizona","Pop":7171646,"Year":"2018","per_US":2.1918233496,"quantile":"2nd"},{"State":"Virginia","Pop":8517685,"Year":"2018","per_US":2.6032044621,"quantile":"1st"},{"State":"Arkansas","Pop":3013825,"Year":"2018","per_US":0.9210956601,"quantile":"3rd"},{"State":"Vermont","Pop":626299,"Year":"2018","per_US":0.1914116748,"quantile":"4th"},{"State":"Utah","Pop":3161105,"Year":"2018","per_US":0.9661078851,"quantile":"3rd"},{"State":"California","Pop":39557045,"Year":"2018","per_US":12.0895614303,"quantile":"1st"},{"State":"Texas","Pop":28701845,"Year":"2018","per_US":8.7719575183,"quantile":"1st"},{"State":"Colorado","Pop":5695564,"Year":"2018","per_US":1.740698044,"quantile":"2nd"},{"State":"Tennessee","Pop":6770010,"Year":"2018","per_US":2.0690739609,"quantile":"2nd"},{"State":"South Dakota","Pop":882235,"Year":"2018","per_US":0.2696317237,"quantile":"4th"},{"State":"Connecticut","Pop":3572665,"Year":"2018","per_US":1.0918902812,"quantile":"3rd"},{"State":"South Carolina","Pop":5084127,"Year":"2018","per_US":1.5538285452,"quantile":"2nd"},{"State":"Delaware","Pop":967171,"Year":"2018","per_US":0.2955901589,"quantile":"4th"},{"State":"Rhode Island","Pop":1057315,"Year":"2018","per_US":0.3231402812,"quantile":"4th"},{"State":"Pennsylvania","Pop":12807060,"Year":"2018","per_US":3.9141381418,"quantile":"1st"},{"State":"District of Columbia","Pop":702455,"Year":"2018","per_US":0.2146867359,"quantile":"4th"},{"State":"Oregon","Pop":4190713,"Year":"2018","per_US":1.2807802567,"quantile":"3rd"},{"State":"Florida","Pop":21299325,"Year":"2018","per_US":6.5095736553,"quantile":"1st"},{"State":"Oklahoma","Pop":3943079,"Year":"2018","per_US":1.2050974939,"quantile":"3rd"},{"State":"Wyoming","Pop":577737,"Year":"2018","per_US":0.1765699878,"quantile":"4th"},{"State":"Georgia","Pop":10519475,"Year":"2018","per_US":3.2149984719,"quantile":"1st"},{"State":"North Dakota","Pop":760077,"Year":"2018","per_US":0.2322973716,"quantile":"4th"},{"State":"Hawaii","Pop":1420491,"Year":"2018","per_US":0.4341353912,"quantile":"4th"},{"State":"North Carolina","Pop":10383620,"Year":"2018","per_US":3.1734779951,"quantile":"1st"},{"State":"New York","Pop":19542209,"Year":"2018","per_US":5.9725577628,"quantile":"1st"},{"State":"Idaho","Pop":1754208,"Year":"2018","per_US":0.5361271394,"quantile":"4th"},{"State":"New Mexico","Pop":2095428,"Year":"2018","per_US":0.6404119804,"quantile":"3rd"},{"State":"Illinois","Pop":12741080,"Year":"2018","per_US":3.8939731051,"quantile":"1st"},{"State":"New Jersey","Pop":8908520,"Year":"2018","per_US":2.7226528117,"quantile":"1st"},{"State":"New Hampshire","Pop":1356458,"Year":"2018","per_US":0.4145654034,"quantile":"4th"},{"State":"Indiana","Pop":6691878,"Year":"2018","per_US":2.0451949878,"quantile":"2nd"},{"State":"Nevada","Pop":3034392,"Year":"2018","per_US":0.9273814181,"quantile":"3rd"},{"State":"Iowa","Pop":3156145,"Year":"2018","per_US":0.9645919927,"quantile":"3rd"},{"State":"Nebraska","Pop":1929268,"Year":"2018","per_US":0.5896295844,"quantile":"3rd"},{"State":"Montana","Pop":1062305,"Year":"2018","per_US":0.3246653423,"quantile":"4th"},{"State":"Kansas","Pop":2911510,"Year":"2018","per_US":0.8898257946,"quantile":"3rd"},{"State":"Missouri","Pop":6126452,"Year":"2018","per_US":1.8723875306,"quantile":"2nd"},{"State":"Kentucky","Pop":4468402,"Year":"2018","per_US":1.365648533,"quantile":"2nd"},{"State":"Mississippi","Pop":2986530,"Year":"2018","per_US":0.9127536675,"quantile":"3rd"},{"State":"Minnesota","Pop":5611179,"Year":"2018","per_US":1.7149080073,"quantile":"2nd"},{"State":"Louisiana","Pop":4659978,"Year":"2018","per_US":1.4241986553,"quantile":"2nd"},{"State":"Michigan","Pop":9995915,"Year":"2018","per_US":3.0549862469,"quantile":"1st"},{"State":"Maine","Pop":1338404,"Year":"2018","per_US":0.4090476773,"quantile":"4th"},{"State":"Massachusetts","Pop":6902149,"Year":"2018","per_US":2.1094587408,"quantile":"2nd"},{"State":"Maryland","Pop":6042718,"Year":"2018","per_US":1.8467964548,"quantile":"2nd"}]